eppaurora/__init__.py
eppaurora/brems.py
eppaurora/conductivity.py
eppaurora/electrons.py
eppaurora/protons.py
eppaurora/recombination.py
eppaurora/spectra.py
eppaurora/ssusi.py
eppaurora/models/__init__.py
eppaurora/models/ssusiq2023.py
eppaurora/models/data/SSUSI_IRgrid_coeffs_f17f18.nc
eppaurora-0.3.1.dist-info/LICENSE
eppaurora-0.3.1.dist-info/METADATA
eppaurora-0.3.1.dist-info/WHEEL
eppaurora-0.3.1.dist-info/top_level.txt
eppaurora-0.3.1.dist-info/RECORD
