Metadata-Version: 2.1
Name: eppaurora
Version: 0.3.1
Summary: Atomspheric ionization from auroral particle precipitation
Home-page: https://github.com/st-bender/pyeppaurora
Author: Stefan Bender
Author-email: stefan.bender@ntnu.no
License: GPLv2
Classifier: Development Status :: 4 - Beta
Classifier: Intended Audience :: Science/Research
Classifier: License :: OSI Approved :: GNU General Public License v2 (GPLv2)
Classifier: Programming Language :: Python
Classifier: Programming Language :: Python :: 2
Classifier: Programming Language :: Python :: 3
Classifier: Topic :: Scientific/Engineering :: Physics
Classifier: Topic :: Utilities
License-File: LICENSE
Requires-Dist: numpy >=1.13.0
Requires-Dist: scipy >=0.9
Provides-Extra: all
Requires-Dist: h5netcdf ; extra == 'all'
Requires-Dist: pytest ; extra == 'all'
Requires-Dist: xarray ; extra == 'all'
Provides-Extra: models
Requires-Dist: h5netcdf ; extra == 'models'
Requires-Dist: xarray ; extra == 'models'
Provides-Extra: tests
Requires-Dist: pytest ; extra == 'tests'
